cyclomonitor/__init__.py
cyclomonitor/__main__.py
cyclomonitor/atcf.py
cyclomonitor/cli.py
cyclomonitor/cyclomonitor.py
cyclomonitor/dir_calc.py
cyclomonitor/errors.py
cyclomonitor/global_vars.py
cyclomonitor/server_vars.py
cyclomonitor/uptime.py
cyclomonitor/ibtracs/__init__.py
cyclomonitor/ibtracs/__main__.py
cyclomonitor/ibtracs/ibtracs_ALL.sql
cyclomonitor/ibtracs/ibtracs_LAST3.sql
cyclomonitor/ibtracs/locales/C.json
cyclomonitor/ibtracs/locales/__init__.py
cyclomonitor/ibtracs/locales/en_US.json
cyclomonitor/locales/C.json
cyclomonitor/locales/__init__.py
cyclomonitor/locales/en_US.json
cyclomonitor/locales/es_US.json
cyclomonitor-2025.7.17.dist-info/licenses/LICENSE
cyclomonitor-2025.7.17.dist-info/METADATA
cyclomonitor-2025.7.17.dist-info/WHEEL
cyclomonitor-2025.7.17.dist-info/top_level.txt
cyclomonitor-2025.7.17.dist-info/RECORD
