Metadata-Version: 2.4
Name: cyclomonitor
Version: 2025.7.17
Summary: Discord bot that helps you keep tabs on tropical cyclones.
Home-page: https://github.com/ntvmb/cyclomonitor
Author: Nathaniel Greenwell
Author-email: Nathaniel Greenwell <nategreenwell@live.com>
Maintainer-email: Nathaniel Greenwell <nategreenwell@live.com>
License:                     GNU AFFERO GENERAL PUBLIC LICENSE
Project-URL: Repository, https://github.com/ntvmb/cyclomonitor.git
Project-URL: Issues, https://github.com/ntvmb/cyclomonitor/issues
Project-URL: Changelog, https://github.com/ntvmb/cyclomonitor/blob/master/CHANGELOG.md
Project-URL: Discord, https://discord.gg/xBHESnJYz5
Keywords: weather,discord,discord bot,discord-py,typhoon,hurricane,tropical cyclone,atcf,py-cord,ibtracs
Classifier: Development Status :: 4 - Beta
Classifier: Intended Audience :: Developers
Classifier: Topic :: Internet
Classifier: Topic :: Scientific/Engineering
Classifier: License :: OSI Approved :: GNU Affero General Public License v3 or later (AGPLv3+)
Classifier: Programming Language :: Python :: 3
Classifier: Programming Language :: Python :: 3.8
Classifier: Programming Language :: Python :: 3.9
Classifier: Programming Language :: Python :: 3.10
Classifier: Programming Language :: Python :: 3.11
Classifier: Programming Language :: Python :: 3.12
Classifier: Programming Language :: Python :: 3.13
Classifier: Programming Language :: Python :: 3 :: Only
Requires-Python: >=3.8
License-File: LICENSE
Requires-Dist: aiohttp>=3.6.0
Requires-Dist: aiofiles>=23.2.1
Provides-Extra: bot
Requires-Dist: py-cord>=2.6.1; extra == "bot"
Requires-Dist: audioop-lts; python_version >= "3.13" and extra == "bot"
Requires-Dist: tendo; extra == "bot"
Dynamic: author
Dynamic: home-page
Dynamic: license-file
Dynamic: requires-python
